<?xml version="1.0" encoding="utf-8"?>
<StructureDefinition xmlns="http://hl7.org/fhir">
  <id value="AllergyIntolerance-SubstanceFocused" />
  <meta>
    <lastUpdated value="2018-02-01T21:21:14.335+01:00" />
  </meta>
  <url value="http://snomed.info/fhir/StructureDefinition/AllergyIntolerance-SubstanceFocused" />
  <version value="0.0.1" />
  <name value="AllergyIntoleranceSubstanceFocused" />
  <status value="draft" />
  <date value="2018-01-18T11:19:41.496+01:00" />
  <fhirVersion value="4.0.0" />
  <kind value="resource" />
  <abstract value="false" />
  <type value="AllergyIntolerance" />
  <baseDefinition value="http://hl7.org/fhir/StructureDefinition/AllergyIntolerance" />
  <derivation value="constraint" />
  <differential>
    <element id="AllergyIntolerance.category">
      <path value="AllergyIntolerance.category" />
      <max value="0" />
    </element>
    <element id="AllergyIntolerance.code">
      <path value="AllergyIntolerance.code" />
      <short value="Code that identifies the substance or product which the patient has an allergy or intolerance to" />
      <definition value="Code for a substance or pharmaceutical product that is considered to be responsible for the adverse reaction risk (e.g., &quot;Latex&quot;), [WHAT ABOUT NEGATION??] or a negated/excluded code for a specific substance or class (e.g., &quot;No latex allergy&quot;) or a general or categorical negated statement (e.g.,  &quot;No known allergy&quot;, &quot;No known drug allergies&quot;)." />
      <constraint>
        <key value="code-1" />
        <severity value="error" />
        <human value="A code or a note must exist" />
        <expression value="code.exists() or note.exists()" />
        <source value="AllergyIntolerance" />
      </constraint>
      <binding>
        <strength value="extensible" />
        <description value="Type of the substance/product." />
        <valueSet value="http://hl7.org/fhir/ValueSet/substance-code" />
      </binding>
    </element>
    <element id="AllergyIntolerance.code.coding.system">
      <path value="AllergyIntolerance.code.coding.system" />
      <fixedUri value="http://snomed.info/sct" />
    </element>
    <element id="AllergyIntolerance.reaction.substance">
      <path value="AllergyIntolerance.reaction.substance" />
      <binding>
        <strength value="extensible" />
      </binding>
    </element>
    <element id="AllergyIntolerance.reaction.manifestation">
      <path value="AllergyIntolerance.reaction.manifestation" />
      <binding>
        <strength value="extensible" />
      </binding>
    </element>
    <element id="AllergyIntolerance.reaction.exposureRoute">
      <path value="AllergyIntolerance.reaction.exposureRoute" />
      <binding>
        <strength value="extensible" />
      </binding>
    </element>
  </differential>
</StructureDefinition>